datastation/__init__.py
datastation/common/__init__.py
datastation/common/batch_processing.py
datastation/common/config.py
datastation/common/csv.py
datastation/common/database.py
datastation/common/find_bags.py
datastation/common/result_writer.py
datastation/common/send_mail.py
datastation/common/utils.py
datastation/common/version_info.py
datastation/dans_bag/__init__.py
datastation/dans_bag/validate_dans_bag.py
datastation/dans_bag_validate.py
datastation/datastation_get_component_versions.py
datastation/dataverse/__init__.py
datastation/dataverse/banner_api.py
datastation/dataverse/builtin_users.py
datastation/dataverse/dataset_api.py
datastation/dataverse/datasets.py
datastation/dataverse/dataverse_api.py
datastation/dataverse/dataverse_client.py
datastation/dataverse/destroy_placeholder_dataset.py
datastation/dataverse/file_api.py
datastation/dataverse/metrics_api.py
datastation/dataverse/metrics_collect.py
datastation/dataverse/notifications.py
datastation/dataverse/permissions_collect.py
datastation/dataverse/roles.py
datastation/dataverse/search_api.py
datastation/dataverse/user_import.py
datastation/deposit_clean_data.py
datastation/deposit_create_report.py
datastation/dv_api.py
datastation/dv_banner.py
datastation/dv_dataset_delete_draft.py
datastation/dv_dataset_destroy.py
datastation/dv_dataset_destroy_migration_placeholder.py
datastation/dv_dataset_edit_metadata.py
datastation/dv_dataset_find_by_role_assignment.py
datastation/dv_dataset_get_attributes.py
datastation/dv_dataset_get_metadata.py
datastation/dv_dataset_get_metadata_export.py
datastation/dv_dataset_lock.py
datastation/dv_dataset_publish.py
datastation/dv_dataset_reindex.py
datastation/dv_dataset_reingest_tabular.py
datastation/dv_dataset_role_assignment.py
datastation/dv_dataset_update_datacite.py
datastation/dv_dataset_verify.py
datastation/dv_dataverse_role_assignment.py
datastation/dv_dataverse_root_collect_permission_overview.py
datastation/dv_dataverse_root_collect_storage_usage.py
dans_datastation_tools-0.53.0.dist-info/LICENSE
dans_datastation_tools-0.53.0.dist-info/METADATA
dans_datastation_tools-0.53.0.dist-info/WHEEL
dans_datastation_tools-0.53.0.dist-info/entry_points.txt
dans_datastation_tools-0.53.0.dist-info/RECORD
