Metadata-Version: 2.1
Name: dans-datastation-tools
Version: 0.53.0
Summary: Command line utilities for Data Station application management
Author: DANS-KNAW
Requires-Python: >=3.9,<4.0
Classifier: Programming Language :: Python :: 3
Classifier: Programming Language :: Python :: 3.9
Classifier: Programming Language :: Python :: 3.10
Classifier: Programming Language :: Python :: 3.11
Classifier: Programming Language :: Python :: 3.12
Requires-Dist: argparse-formatter (>=1.4,<2.0)
Requires-Dist: bs4 (>=0.0.1,<0.0.2)
Requires-Dist: dicttoxml (>=1.7.4,<2.0.0)
Requires-Dist: lxml (>=4.8.0,<5.0.0)
Requires-Dist: psycopg (>=3.1.8,<4.0.0)
Requires-Dist: pyYAML (>=6.0,<7.0)
Requires-Dist: requests (>=2.28.2,<3.0.0)
Requires-Dist: rich (>=13.7.0,<14.0.0)
